LICENSE.txt
MANIFEST.in
README.txt
examples.py
setup.py
progressbar/__init__.py
progressbar/compat.py
progressbar/progressbar.py
progressbar/widgets.py
progressbar33.egg-info/PKG-INFO
progressbar33.egg-info/SOURCES.txt
progressbar33.egg-info/dependency_links.txt
progressbar33.egg-info/top_level.txt